[
  {
    "judul": "بِسْمِ اللّٰهِ الرَّحْمٰنِ الرَّحِيْمِ",
    "arab": "",
    "latin": "",
    "terjemah": "Dengan menyebut nama Allah Yang Maha Pengasih lagi Maha Penyayang"
  },
  {
    "judul": "",
    "arab": "يَا رَبِّ  صَلِّ  عَلَى مُحَمَّدْ۞ حَبِيبِكَ الشَّافِعِ الْمُشَفَّعْ",
    "latin": "",
    "terjemah": "Ya Allah limpahkanlah shalawat atas Muhammad ۞ Kekasih- Mu pemilik syafa’at yang dilimpahi syafa’at- Mu"
  },
  {
    "judul": "",
    "arab": "يَا رَبِّ صَلِّ عَلَى مُحَمَّدْ ۞ يَا رَبِّ صَلِّ عَلَيْهِ وَ سَلِّمْ",
    "latin": "",
    "terjemah": "Yaa Allah, limpahkanlah shalawat atas Muhammad ۞ Yaa Allah, limpahkanlah shalawat dan salam sejahtera atasnya"
  },
  {
    "judul": "",
    "arab": "يَا رَبِّ صَلِّ عَلَى مُحَمَّدْ ۞ أَعْلَى الْوَرَي رُتْبَةً وَأَرْفَعْ",
    "latin": "",
    "terjemah": "Yaa Allah, limpahkanlah shalawat atas Muhammad ۞ Semulia-mulia ciptaan, dalam keagungan dan derajatnya"
  },
  {
    "judul": "",
    "arab": "",
    "latin": "",
    "terjemah": ""
  },
  {
    "judul": "",
    "arab": "",
    "latin": "",
    "terjemah": ""
  },
  {
    "judul": "",
    "arab": "",
    "latin": "",
    "terjemah": ""
  },
  {
    "judul": "",
    "arab": "",
    "latin": "",
    "terjemah": ""
  },
  {
    "judul": "",
    "arab": "",
    "latin": "",
    "terjemah": ""
  },
  {
    "judul": "",
    "arab": "",
    "latin": "",
    "terjemah": ""
  },
  {
    "judul": "",
    "arab": "",
    "latin": "",
    "terjemah": ""
  },
  {
    "judul": "",
    "arab": "",
    "latin": "",
    "terjemah": ""
  },
  {
    "judul": "",
    "arab": "",
    "latin": "",
    "terjemah": ""
  },
  {
    "judul": "",
    "arab": "",
    "latin": "",
    "terjemah": ""
  },
  {
    "judul": "",
    "arab": "",
    "latin": "",
    "terjemah": ""
  },
  {
    "judul": "",
    "arab": "",
    "latin": "",
    "terjemah": ""
  },
  {
    "judul": "",
    "arab": "",
    "latin": "",
    "terjemah": ""
  },
  {
    "judul": "",
    "arab": "",
    "latin": "",
    "terjemah": ""
  },
  {
    "judul": "",
    "arab": "",
    "latin": "",
    "terjemah": ""
  }
]
